faststore/__init__.py
faststore/error.py
faststore/model.py
faststore/validator.py
faststore-0.1.5.dist-info/LICENSE
faststore-0.1.5.dist-info/WHEEL
faststore-0.1.5.dist-info/METADATA
faststore-0.1.5.dist-info/RECORD
