Metadata-Version: 2.1
Name: faststore
Version: 0.1.5
Summary: Faster development using Firestore
Home-page: https://github.com/sarmadgulzar/faststore
Author: Sarmad Gulzar
Author-email: sarmadgulzar@hotmail.com
Requires-Python: >=3.6
Classifier: Operating System :: OS Independent
Classifier: License :: OSI Approved :: MIT License
Classifier: Programming Language :: Python :: 3
Classifier: Programming Language :: Python :: 3 :: Only
Classifier: Programming Language :: Python :: 3.6
Classifier: Programming Language :: Python :: 3.7
Classifier: Programming Language :: Python :: 3.8
Classifier: Programming Language :: Python :: 3.9
Requires-Dist: pydantic==1.8.2
Requires-Dist: google-cloud-firestore==2.1.3
